aioldap/__init__.py
aioldap/connection.py
aioldap/exceptions.py
aioldap-0.4.2.dist-info/METADATA
aioldap-0.4.2.dist-info/RECORD
aioldap-0.4.2.dist-info/WHEEL
aioldap-0.4.2.dist-info/top_level.txt
