Metadata-Version: 2.1
Name: aioldap
Version: 0.4.2
Summary: Async ldap library sorta based off ldap3
Home-page: https://github.com/terrycain/aioldap
Author: Terry Cain
Author-email: terry@terrys-home.co.uk
License: Apache 2
Keywords: aioldap
Platform: UNKNOWN
Classifier: Development Status :: 2 - Pre-Alpha
Classifier: Intended Audience :: Developers
Classifier: License :: OSI Approved :: Apache Software License
Classifier: Natural Language :: English
Classifier: Programming Language :: Python :: 3
Classifier: Programming Language :: Python :: 3.6
Classifier: Programming Language :: Python :: 3.7
Requires-Dist: ldap3 (==2.5)
